[{"DAY\nTIMING              ":"10:00 - 11:00","MONDAY ":"6B71:CD:SK:(N-606)\n 6B72:CD:PS:(N-606)","TUESDAY":"6B7:ML:TM2:N-606","WEDNESDAY(online)":"6B7:CS:F1","THURSDAY(online)":"6B7:MAD:F1","FRIDAY ":"6B71:GPU:MK:(N-607)\n 6B72:GPU:AT:(N-607)"},{"DAY\nTIMING              ":"11:00 - 12:00","MONDAY ":"6B71:CD:SK:(N-606)\n 6B72:CD:PS:(N-606)","TUESDAY":"6B7:ML:TM2:N-606","WEDNESDAY(online)":"6B7:CS:F1","THURSDAY(online)":"6B7:MAD:F1","FRIDAY ":"6B71:GPU:MK:(N-607)\n 6B72:GPU:AT:(N-607)"},{"DAY\nTIMING              ":"12:00 - 01:00","MONDAY ":"RECESS","TUESDAY":"RECESS","WEDNESDAY(online)":"RECESS","THURSDAY(online)":"RECESS","FRIDAY ":"RECESS"},{"DAY\nTIMING              ":"01:00 - 01:50","MONDAY ":"6B7:CD:PS(N-606)","TUESDAY":"6B7:CD:PS(N-606)","WEDNESDAY(online)":"6B7:MAD:F1","THURSDAY(online)":"6B7:CS:F1","FRIDAY ":"LIBARARY"},{"DAY\nTIMING              ":"01:50 - 02:40","MONDAY ":"6B7:ML:TM2:N-201","TUESDAY":"6B7:GPU:KS(N-606)","WEDNESDAY(online)":"LIBRARY","THURSDAY(online)":"LIBRARY","FRIDAY ":"LIBARARY"},{"DAY\nTIMING              ":"02:40 - 03:00","MONDAY ":"RECESS","TUESDAY":"RECESS","WEDNESDAY(online)":"RECESS","THURSDAY(online)":"RECESS","FRIDAY ":"RECESS"},{"DAY\nTIMING              ":"03:00 - 04:00","MONDAY ":"6B7:GPU:KS(N-606)","TUESDAY":"6B7:ML:TM2:N-201","WEDNESDAY(online)":"6B71:CS:F1 6B72:CS:F1","THURSDAY(online)":"6B71:MAD:F1 6B71:MAD:F1","FRIDAY ":"6B7:CD:PS(N-605)"},{"DAY\nTIMING              ":"04:00 - 05:00","MONDAY ":"6B7:ES: (N-606)","TUESDAY":"6B7:ML:TM2:N-201","WEDNESDAY(online)":"6B71:CS:F1 6B72:CS:F1","THURSDAY(online)":"6B71:MAD:F1 6B71:MAD:F1","FRIDAY ":"6B7:GPU:KS(N-605)"}]